reals/__init__.py
reals/_algebraic_computation.py
reals/_bihomographic.py
reals/_compare.py
reals/_computation.py
reals/_constants.py
reals/_exponential.py
reals/_homographic.py
reals/_inverse.py
reals/_logarithm.py
reals/_normalize.py
reals/_quadratic_computation.py
reals/_real.py
reals/_sqrt.py
reals/_term.py
reals/_trigonometric.py
reals/_utils.py
reals/approximation.py
reals-0.0.5.dist-info/LICENSE
reals-0.0.5.dist-info/METADATA
reals-0.0.5.dist-info/WHEEL
reals-0.0.5.dist-info/top_level.txt
reals-0.0.5.dist-info/RECORD
