Metadata-Version: 2.1
Name: reals
Version: 0.0.5
Summary: A lightweight python3 library for arithmetic with real numbers.
Home-page: https://github.com/rubenvannieuwpoort/reals
Author: Ruben van Nieuwpoort
Author-email: ruben@vannieuwpoort.dev
License: MIT
Project-URL: Bug Tracker, https://github.com/rubenvannieuwpoort/reals/issues
Classifier: Programming Language :: Python :: 3
Classifier: Programming Language :: Python :: 3.10
Classifier: License :: OSI Approved :: MIT License
Classifier: Operating System :: OS Independent
Requires-Python: >=3.10
License-File: LICENSE
Provides-Extra: dev
Requires-Dist: pytest ==7.4.0 ; extra == 'dev'
Requires-Dist: mypy ==1.5.0 ; extra == 'dev'
Requires-Dist: flake8 ==6.1.0 ; extra == 'dev'
Requires-Dist: pytest-timeout ==2.1.0 ; extra == 'dev'
